greenstream_config/__init__.py
greenstream_config/namespace_helpers.py
greenstream_config/types.py
greenstream_config/test/test_namespace_helpers.py
greenstream_config/test/test_types.py
greenstream_config-4.5.1.dist-info/METADATA
greenstream_config-4.5.1.dist-info/WHEEL
greenstream_config-4.5.1.dist-info/top_level.txt
greenstream_config-4.5.1.dist-info/zip-safe
greenstream_config-4.5.1.dist-info/RECORD
